{
  "Hardware": {
    "DcMotors": {
      "Drive": {
        "list": [
          "Front Left Motor",
          "Front Right Motor",
          "Back Left Motor",
          "Back Right Motor"
        ],
        "Front Left Motor": {
          "name": "FLM",
          "Port": "C-0",
          "Reverse": false,
          "BrakeType": "brake"
        },
        "Front Right Motor": {
          "name": "FRM",
          "Port": "E-0",
          "Reverse": true,
          "BrakeType": "brake"
        },
        "Back Left Motor": {
          "name": "BLM",
          "Port": "C-1",
          "Reverse": false,
          "BrakeType": "brake"
        },
        "Back Right Motor": {
          "name": "BRM",
          "Port": "E-1",
          "Reverse": true,
          "BrakeType": "brake"
        }
      },
      "Lift": {
        "name": "lift",
        "Port": "E-2",
        "Reverse": true,
        "BrakeType": "brake"
      },
      "In_Out": {
        "name": "inout",
        "port": "C-2",
        "Reverse": false,
        "BrakeType": "brake"
      }
    },
    "Sensors": {
      "potentiometer": {
        "name": "POE",
        "Port": "C-A0"
      }
    },
    "Servos": {
      "Test": {
        "name": "test",
        "port": "",
        "Location": "This is located here on the robot"
      }
    }
  },
  "Field": {
    "location": {
      "red": {
        "StartingLoc": {
          "First": [],
          "Second": []
        },
        "hub": {
          "side 1": [],
          "side 2": []
        },
        "Warehouse": [],
        "Depot": []
      },
      "blue": {
        "StartingLoc": {
          "First": [],
          "Second": []
        },
        "hub": {
          "side 1": [],
          "side 2": []
        },
        "Warehouse": [],
        "Depot": []
      }
    },
    "constants": {

    }
  }
}